tests/fixtures/verilog/03_fsm.v
module seqdet(input clk, rst, x, output reg y);
  localparam S0 = 2'd0, S1 = 2'd1, S2 = 2'd2, S3 = 2'd3;
  reg [1:0] state, next;
  always @(posedge clk) if (rst) state <= S0; else state <= next;
  always @(*) begin
    next = state; y = 0;
    case (state)
      S0: next = x ? S1 : S0;
      S1: next = x ? S1 : S2;
      S2: next = x ? S3 : S0;
      S3: begin y = 1; next = x ? S1 : S2; end
      default: next = S0;
    endcase
  end
endmodule
module tb;
  reg clk = 0, rst = 1, x = 0; wire y;
  seqdet d(clk, rst, x, y);
  always #5 clk = ~clk;
  reg [15:0] pattern = 16'b1011_0101_1010_1101;
  integer k;
  initial begin
    @(negedge clk) rst = 0;
    for (k = 15; k >= 0; k = k - 1) begin x = pattern[k]; @(negedge clk) $display("t=%0t x=%b state=%d y=%b", $time, x, d.state, y); end
    $finish;
  end
endmodule

tests/fixtures/verilog/03_fsm.vcd
$date
	Fri Oct  2 09:18:37 2026
$end
$version
	Icarus Verilog
$end
$timescale
	1s
$end
$scope module tb $end
$var wire 1 ! y $end
$var reg 1 " clk $end
$var reg 16 # pattern [15:0] $end
$var reg 1 $ rst $end
$var reg 1 % x $end
$var integer 32 & k [31:0] $end
$scope module d $end
$var wire 1 " clk $end
$var wire 1 $ rst $end
$var wire 1 % x $end
$var parameter 2 ' S0 $end
$var parameter 2 ( S1 $end
$var parameter 2 ) S2 $end
$var parameter 2 * S3 $end
$var reg 2 + next [1:0] $end
$var reg 2 , state [1:0] $end
$var reg 1 ! y $end
$upscope $end
$upscope $end
$enddefinitions $end
$comment Show the parameter values. $end
$dumpall
b11 *
b10 )
b1 (
b0 '
$end
#0
$dumpvars
bx ,
b0 +
bx &
0%
1$
b1011010110101101 #
0"
0!
$end
#5
b0 ,
1"
#10
b1 +
1%
b1111 &
0$
0"
#15
b1 ,
1"
#20
b10 +
0%
b1110 &
0"
#25
b0 +
b10 ,
1"
#30
b11 +
1%
b1101 &
0"
#35
b1 +
1!
b11 ,
1"
#40
b1100 &
0"
#45
0!
b1 ,
1"
#50
b10 +
0%
b1011 &
0"
#55
b0 +
b10 ,
1"
#60
b11 +
1%
b1010 &
0"
#65
b1 +
1!
b11 ,
1"
#70
1!
b10 +
0%
b1001 &
0"
#75
b0 +
0!
b10 ,
1"
#80
b11 +
1%
b1000 &
0"
#85
b1 +
1!
b11 ,
1"
#90
b111 &
0"
#95
0!
b1 ,
1"
#100
b10 +
0%
b110 &
0"
#105
b0 +
b10 ,
1"
#110
b11 +
1%
b101 &
0"
#115
b1 +
1!
b11 ,
1"
#120
1!
b10 +
0%
b100 &
0"
#125
b0 +
0!
b10 ,
1"
#130
b11 +
1%
b11 &
0"
#135
b1 +
1!
b11 ,
1"
#140
b10 &
0"
#145
0!
b1 ,
1"
#150
b10 +
0%
b1 &
0"
#155
b0 +
b10 ,
1"
#160
b11 +
1%
b0 &
0"
#165
b1 +
1!
b11 ,
1"
#170
b11111111111111111111111111111111 &
0"
