tests/fixtures/verilog/06_mem.v
module ram(input clk, we, input [3:0] addr, input [7:0] din, output [7:0] dout);
  reg [7:0] mem [0:15];
  always @(posedge clk) if (we) mem[addr] <= din;
  assign dout = mem[addr];
endmodule
module tb;
  reg clk = 0, we = 0; reg [3:0] addr = 0; reg [7:0] din = 0; wire [7:0] dout;
  ram r(clk, we, addr, din, dout);
  always #1 clk = ~clk;
  integer k;
  initial begin
    for (k = 0; k < 16; k = k + 1) begin @(negedge clk); we = 1; addr = k; din = k * 7 + 3; end
    @(negedge clk) we = 0;
    for (k = 0; k < 16; k = k + 4) begin addr = k; #2 $display("mem[%0d] = %d (%h)", addr, dout, dout); end
    $finish;
  end
endmodule

tests/fixtures/verilog/06_mem.vcd
$date
	Fri Oct  2 09:18:37 2026
$end
$version
	Icarus Verilog
$end
$timescale
	1s
$end
$scope module tb $end
$var wire 8 ! dout [7:0] $end
$var reg 4 " addr [3:0] $end
$var reg 1 # clk $end
$var reg 8 $ din [7:0] $end
$var reg 1 % we $end
$var integer 32 & k [31:0] $end
$scope module r $end
$var wire 4 ' addr [3:0] $end
$var wire 1 # clk $end
$var wire 8 ( din [7:0] $end
$var wire 8 ) dout [7:0] $end
$var wire 1 % we $end
$upscope $end
$upscope $end
$enddefinitions $end
$comment Show the parameter values. $end
$dumpall
$end
#0
$dumpvars
bx )
b0 (
b0 '
b0 &
0%
b0 $
0#
b0 "
bx !
$end
#1
1#
#2
b1 &
b11 $
b11 (
1%
0#
#3
b11 !
b11 )
1#
#4
b10 &
b1010 $
b1010 (
bx !
bx )
b1 "
b1 '
0#
#5
b1010 !
b1010 )
1#
#6
b11 &
b10001 $
b10001 (
bx !
bx )
b10 "
b10 '
0#
#7
b10001 !
b10001 )
1#
#8
b100 &
b11000 $
b11000 (
bx !
bx )
b11 "
b11 '
0#
#9
b11000 !
b11000 )
1#
#10
b101 &
b11111 $
b11111 (
bx !
bx )
b100 "
b100 '
0#
#11
b11111 !
b11111 )
1#
#12
b110 &
b100110 $
b100110 (
bx !
bx )
b101 "
b101 '
0#
#13
b100110 !
b100110 )
1#
#14
b111 &
b101101 $
b101101 (
bx !
bx )
b110 "
b110 '
0#
#15
b101101 !
b101101 )
1#
#16
b1000 &
b110100 $
b110100 (
bx !
bx )
b111 "
b111 '
0#
#17
b110100 !
b110100 )
1#
#18
b1001 &
b111011 $
b111011 (
bx !
bx )
b1000 "
b1000 '
0#
#19
b111011 !
b111011 )
1#
#20
b1010 &
b1000010 $
b1000010 (
bx !
bx )
b1001 "
b1001 '
0#
#21
b1000010 !
b1000010 )
1#
#22
b1011 &
b1001001 $
b1001001 (
bx !
bx )
b1010 "
b1010 '
0#
#23
b1001001 !
b1001001 )
1#
#24
b1100 &
b1010000 $
b1010000 (
bx !
bx )
b1011 "
b1011 '
0#
#25
b1010000 !
b1010000 )
1#
#26
b1101 &
b1010111 $
b1010111 (
bx !
bx )
b1100 "
b1100 '
0#
#27
b1010111 !
b1010111 )
1#
#28
b1110 &
b1011110 $
b1011110 (
bx !
bx )
b1101 "
b1101 '
0#
#29
b1011110 !
b1011110 )
1#
#30
b1111 &
b1100101 $
b1100101 (
bx !
bx )
b1110 "
b1110 '
0#
#31
b1100101 !
b1100101 )
1#
#32
b10000 &
b1101100 $
b1101100 (
bx !
bx )
b1111 "
b1111 '
0#
#33
b1101100 !
b1101100 )
1#
#34
b11 !
b11 )
b0 "
b0 '
b0 &
0%
0#
#35
1#
#36
0#
b11111 !
b11111 )
b100 "
b100 '
b100 &
#37
1#
#38
0#
b111011 !
b111011 )
b1000 "
b1000 '
b1000 &
#39
1#
#40
0#
b1010111 !
b1010111 )
b1100 "
b1100 '
b1100 &
#41
1#
#42
0#
b10000 &
