tests/fixtures/verilog/08_shift_reg.v
module tb;
  reg clk = 0; reg [7:0] sr = 8'b1; reg [3:0] cnt = 0; wire tick = (cnt == 4'd9);
  always #3 clk = !clk;
  always @(posedge clk) begin cnt <= tick ? 0 : cnt + 1; if (tick) sr <= {sr[6:0], sr[7]}; end
  initial begin #200; $display("sr=%b cnt=%d", sr, cnt); end
  initial begin $monitor("%0t: sr=%b", $time, sr); #250 $finish; end
endmodule

tests/fixtures/verilog/08_shift_reg.vcd
$date
	Fri Oct  2 09:18:37 2026
$end
$version
	Icarus Verilog
$end
$timescale
	1s
$end
$scope module tb $end
$var wire 1 ! tick $end
$var reg 1 " clk $end
$var reg 4 # cnt [3:0] $end
$var reg 8 $ sr [7:0] $end
$upscope $end
$enddefinitions $end
$comment Show the parameter values. $end
$dumpall
$end
#0
$dumpvars
b1 $
b0 #
0"
0!
$end
#3
b1 #
1"
#6
0"
#9
b10 #
1"
#12
0"
#15
b11 #
1"
#18
0"
#21
b100 #
1"
#24
0"
#27
b101 #
1"
#30
0"
#33
b110 #
1"
#36
0"
#39
b111 #
1"
#42
0"
#45
b1000 #
1"
#48
0"
#51
1!
b1001 #
1"
#54
0"
#57
b10 $
0!
b0 #
1"
#60
0"
#63
b1 #
1"
#66
0"
#69
b10 #
1"
#72
0"
#75
b11 #
1"
#78
0"
#81
b100 #
1"
#84
0"
#87
b101 #
1"
#90
0"
#93
b110 #
1"
#96
0"
#99
b111 #
1"
#102
0"
#105
b1000 #
1"
#108
0"
#111
1!
b1001 #
1"
#114
0"
#117
b100 $
0!
b0 #
1"
#120
0"
#123
b1 #
1"
#126
0"
#129
b10 #
1"
#132
0"
#135
b11 #
1"
#138
0"
#141
b100 #
1"
#144
0"
#147
b101 #
1"
#150
0"
#153
b110 #
1"
#156
0"
#159
b111 #
1"
#162
0"
#165
b1000 #
1"
#168
0"
#171
1!
b1001 #
1"
#174
0"
#177
b1000 $
0!
b0 #
1"
#180
0"
#183
b1 #
1"
#186
0"
#189
b10 #
1"
#192
0"
#195
b11 #
1"
#198
0"
#201
b100 #
1"
#204
0"
#207
b101 #
1"
#210
0"
#213
b110 #
1"
#216
0"
#219
b111 #
1"
#222
0"
#225
b1000 #
1"
#228
0"
#231
1!
b1001 #
1"
#234
0"
#237
b10000 $
0!
b0 #
1"
#240
0"
#243
b1 #
1"
#246
0"
#249
b10 #
1"
